smartdns/__init__.py
smartdns/finder.py
smartdns/monitor.py
smartdns/runner.py
smartdns/sdns.py
smartdns/server.py
smartdns-3.6.2.dist-info/LICENCE.txt
smartdns-3.6.2.dist-info/METADATA
smartdns-3.6.2.dist-info/WHEEL
smartdns-3.6.2.dist-info/entry_points.txt
smartdns-3.6.2.dist-info/top_level.txt
smartdns-3.6.2.dist-info/RECORD
