Metadata-Version: 2.1
Name: smartdns
Version: 3.6.2
Summary: An Intelligent DNS Similar to DNSPod
Home-page: https://github.com/duanhongyi/smartdns
Author: duanhongyi
Author-email: duanhyi@gmail.com
License: BSD
Platform: all platform
Requires-Dist: pyopenssl
Requires-Dist: pyyaml
Requires-Dist: service-identity
Requires-Dist: setuptools
Requires-Dist: twisted
